pysgtsnepi/__init__.py
pysgtsnepi/core.py
pysgtsnepi/utils/__init__.py
pysgtsnepi/utils/sgtsne_lambda_equalization.py
pysgtsnepi-0.1.3.dist-info/LICENSE
pysgtsnepi-0.1.3.dist-info/METADATA
pysgtsnepi-0.1.3.dist-info/WHEEL
pysgtsnepi-0.1.3.dist-info/top_level.txt
pysgtsnepi-0.1.3.dist-info/RECORD
