Metadata-Version: 2.1
Name: pysgtsnepi
Version: 0.1.3
Summary: A Python package for SGtSNEpi
Home-page: https://github.com/qqgjyx/pysgtsnepi
Author: Juntang Wang
Author-email: jw853@duke.edu
Project-URL: Bug Tracker, https://github.com/qqgjyx/pysgtsnepi/issues
Classifier: Programming Language :: Python :: 3
Classifier: License :: OSI Approved :: MIT License
Classifier: Operating System :: OS Independent
Requires-Python: >=3.8
License-File: LICENSE
Requires-Dist: numpy
Requires-Dist: matplotlib
Requires-Dist: seaborn
Requires-Dist: scipy
Requires-Dist: scikit-learn
